[
  {
    "rgn_cd": "NW",
    "grp_nm": "Group A",
    "grp_id_nb": "12345",
    "grp_orig_eff_dt": "1983-08-01 00:00:00.000",
    "lob_nm": "Life",
    "region_ven_nb": "001",
    "comp_type": "Broker",
    "firm_id": "F001",
    "firm_nm": "Firm A",
    "sc_group_owner_nm": "Owner A",
    "Email": "broker.a@firma.com",
    "Formula_Firm_Location_Source_System__c": "BPRS",
    "sc_account_ik": "A001",
    "sc_parent_account_nm": "Parent Firm A",
    "record_type_name": "Record Type A",
    "sc_firm_status": "Appointed",
    "sc_firm_nm": "Firm A",
    "sc_broker_email": "broker.a@firma.com",
    "sc_broker_nm": "Broker A",
    "sc_broker_contact_phone": "123-456-7890",
    "sc_broker_id": "B001"
  },
  {
    "rgn_cd": "NW",
    "grp_nm": "Group B",
    "grp_id_nb": "12346",
    "grp_orig_eff_dt": "1983-08-01 00:00:00.000",
    "lob_nm": "Health",
    "region_ven_nb": "002",
    "comp_type": "Broker",
    "firm_id": "F002",
    "firm_nm": "Firm B",
    "sc_group_owner_nm": "Owner B",
    "Email": "broker.b@firmb.com",
    "Formula_Firm_Location_Source_System__c": "BPRS",
    "sc_account_ik": "A002",
    "sc_parent_account_nm": "Parent Firm B",
    "record_type_name": "Record Type B",
    "sc_firm_status": "Appointed",
    "sc_firm_nm": "Firm B",
    "sc_broker_email": "broker.b@firmb.com",
    "sc_broker_nm": "Broker B",
    "sc_broker_contact_phone": "123-456-7891",
    "sc_broker_id": "B002"
  },
  {
    "rgn_cd": "NW",
    "grp_nm": "Group C",
    "grp_id_nb": "12347",
    "grp_orig_eff_dt": "1983-08-01 00:00:00.000",
    "lob_nm": "Auto",
    "region_ven_nb": "003",
    "comp_type": "Broker",
    "firm_id": "F003",
    "firm_nm": "Firm C",
    "sc_group_owner_nm": "Owner C",
    "Email": "broker.c@firmc.com",
    "Formula_Firm_Location_Source_System__c": "BPRS",
    "sc_account_ik": "A003",
    "sc_parent_account_nm": "Parent Firm C",
    "record_type_name": "Record Type C",
    "sc_firm_status": "Appointed",
    "sc_firm_nm": "Firm C",
    "sc_broker_email": "broker.c@firmc.com",
    "sc_broker_nm": "Broker C",
    "sc_broker_contact_phone": "123-456-7892",
    "sc_broker_id": "B003"
  },
  {
    "rgn_cd": "NW",
    "grp_nm": "Group D",
    "grp_id_nb": "12348",
    "grp_orig_eff_dt": "1983-08-01 00:00:00.000",
    "lob_nm": "Property",
    "region_ven_nb": "004",
    "comp_type": "Broker",
    "firm_id": "F004",
    "firm_nm": "Firm D",
    "sc_group_owner_nm": "Owner D",
    "Email": "broker.d@firmd.com",
    "Formula_Firm_Location_Source_System__c": "BPRS",
    "sc_account_ik": "A004",
    "sc_parent_account_nm": "Parent Firm D",
    "record_type_name": "Record Type D",
    "sc_firm_status": "Appointed",
    "sc_firm_nm": "Firm D",
    "sc_broker_email": "broker.d@firmd.com",
    "sc_broker_nm": "Broker D",
    "sc_broker_contact_phone": "123-456-7893",
    "sc_broker_id": "B004"
  },
  {
    "rgn_cd": "NW",
    "grp_nm": "Group E",
    "grp_id_nb": "12349",
    "grp_orig_eff_dt": "1983-08-01 00:00:00.000",
    "lob_nm": "Marine",
    "region_ven_nb": "005",
    "comp_type": "Broker",
    "firm_id": "F005",
    "firm_nm": "Firm E",
    "sc_group_owner_nm": "Owner E",
    "Email": "broker.e@firme.com",
    "Formula_Firm_Location_Source_System__c": "BPRS",
    "sc_account_ik": "A005",
    "sc_parent_account_nm": "Parent Firm E",
    "record_type_name": "Record Type E",
    "sc_firm_status": "Appointed",
    "sc_firm_nm": "Firm E",
    "sc_broker_email": "broker.e@firme.com",
    "sc_broker_nm": "Broker E",
    "sc_broker_contact_phone": "123-456-7894",
    "sc_broker_id": "B005"
  },
  {
    "rgn_cd": "NW",
    "grp_nm": "Group F",
    "grp_id_nb": "12350",
    "grp_orig_eff_dt": "1983-08-01 00:00:00.000",
    "lob_nm": "Aviation",
    "region_ven_nb": "006",
    "comp_type": "Broker",
    "firm_id": "F006",
    "firm_nm": "Firm F",
    "sc_group_owner_nm": "Owner F",
    "Email": "broker.f@firmf.com",
    "Formula_Firm_Location_Source_System__c": "BPRS",
    "sc_account_ik": "A006",
    "sc_parent_account_nm": "Parent Firm F",
    "record_type_name": "Record Type F",
    "sc_firm_status": "Appointed",
    "sc_firm_nm": "Firm F",
    "sc_broker_email": "broker.f@firmf.com",
    "sc_broker_nm": "Broker F",
    "sc_broker_contact_phone": "123-456-7895",
    "sc_broker_id": "B006"
  },
  {
    "rgn_cd": "NW",
    "grp_nm": "Group G",
    "grp_id_nb": "12351",
    "grp_orig_eff_dt": "1983-08-01 00:00:00.000",
    "lob_nm": "Travel",
    "region_ven_nb": "007",
    "comp_type": "Broker",
    "firm_id": "F007",
    "firm_nm": "Firm G",
    "sc_group_owner_nm": "Owner G",
    "Email": "broker.g@firmg.com",
    "Formula_Firm_Location_Source_System__c": "BPRS",
    "sc_account_ik": "A007",
    "sc_parent_account_nm": "Parent Firm G",
    "record_type_name": "Record Type G",
    "sc_firm_status": "Appointed",
    "sc_firm_nm": "Firm G",
    "sc_broker_email": "broker.g@firmg.com",
    "sc_broker_nm": "Broker G",
    "sc_broker_contact_phone": "123-456-7896",
    "sc_broker_id": "B007"
  },
  {
    "rgn_cd": "NW",
    "grp_nm": "Group H",
    "grp_id_nb": "12352",
    "grp_orig_eff_dt": "1983-08-01 00:00:00.000",
    "lob_nm": "Health",
    "region_ven_nb": "008",
    "comp_type": "Broker",
    "firm_id": "F008",
    "firm_nm": "Firm H",
    "sc_group_owner_nm": "Owner H",
    "Email": "broker.h@firmh.com",
    "Formula_Firm_Location_Source_System__c": "BPRS",
    "sc_account_ik": "A008",
    "sc_parent_account_nm": "Parent Firm H",
    "record_type_name": "Record Type H",
    "sc_firm_status": "Appointed",
    "sc_firm_nm": "Firm H",
    "sc_broker_email": "broker.h@firmh.com",
    "sc_broker_nm": "Broker H",
    "sc_broker_contact_phone": "123-456-7897",
    "sc_broker_id": "B008"
  },
  {
    "rgn_cd": "NW",
    "grp_nm": "Group I",
    "grp_id_nb": "12353",
    "grp_orig_eff_dt": "1983-08-01 00:00:00.000",
    "lob_nm": "Life",
    "region_ven_nb": "009",
    "comp_type": "Broker",
    "firm_id": "F009",
    "firm_nm": "Firm I",
    "sc_group_owner_nm": "Owner I",
    "Email": "broker.i@firmi.com",
    "Formula_Firm_Location_Source_System__c": "BPRS",
    "sc_account_ik": "A009",
    "sc_parent_account_nm": "Parent Firm I",
    "record_type_name": "Record Type I",
    "sc_firm_status": "Appointed",
    "sc_firm_nm": "Firm I",
    "sc_broker_email": "broker.i@firmi.com",
    "sc_broker_nm": "Broker I",
    "sc_broker_contact_phone": "123-456-7898",
    "sc_broker_id": "B009"
  },
  {
    "rgn_cd": "NW",
    "grp_nm": "Group J",
    "grp_id_nb": "12354",
    "grp_orig_eff_dt": "1983-08-01 00:00:00.000",
    "lob_nm": "Property",
    "region_ven_nb": "010",
    "comp_type": "Broker",
    "firm_id": "F010",
    "firm_nm": "Firm J",
    "sc_group_owner_nm": "Owner J",
    "Email": "broker.j@firmj.com",
    "Formula_Firm_Location_Source_System__c": "BPRS",
    "sc_account_ik": "A010",
    "sc_parent_account_nm": "Parent Firm J",
    "record_type_name": "Record Type J",
    "sc_firm_status": "Appointed",
    "sc_firm_nm": "Firm J",
    "sc_broker_email": "broker.j@firmj.com",
    "sc_broker_nm": "Broker J",
    "sc_broker_contact_phone": "123-456-7899",
    "sc_broker_id": "B010"
  }
]
